{"/action/reagent/acts-on": 22, "/action/method/using": 1, "/action/reagent/using": 2, "/action/location/site": 6, "/action/device/using": 1, "/action/reagent/site": 3, "/action/location/acts-on": 5, "/action/numerical/count": 2, "/action/reagent/creates": 1, "/action/mention/acts-on": 2, "/action/time/setting": 8, "/action/speed/setting": 4, "/action/modifier/mod-link": 2, "/action/temperature/setting": 10, "/reagent/amount/measure": 12, "/reagent/reagent/or": 1, "/action/generic-measure/setting": 5, "/reagent/concentration/measure": 1, "/modifier/time/setting": 1, "/temperature/temperature/or": 1, "/reagent/modifier/mod-link": 1}